torch_radon24/__init__.py
torch_radon24/radon.py
torch_radon24/utils.py
torch_radon24-1.6.dist-info/LICENSE
torch_radon24-1.6.dist-info/METADATA
torch_radon24-1.6.dist-info/WHEEL
torch_radon24-1.6.dist-info/top_level.txt
torch_radon24-1.6.dist-info/RECORD
